{"cn_engineering_index.md":"_F_YFM2y","cn_front-end_base_js-docs_index.md":"43vSlses","cn_front-end_frame_index.md":"dYcFnOwq","index.md":"I6no3Rhw","cn_back-end_nestjs_与mysql.md":"2nZ2JWh_","cn_mx-components_index.md":"XT6hAsH-","cn_back-end_nestjs_异常过滤器.md":"TovL6e7T","cn_embedded-system_esp8266_control.md":"65YtGraM","cn_back-end_nestjs_中间件.md":"VcA-e1RC","cn_back-end_nestjs_管道.md":"8SPNADMz","cn_back-end_nestjs_practice_intergrate-with-vercel.md":"0ijG_ol4","cn_back-end_nestjs_控制器.md":"O8cnttkP","en_index.md":"rUmKVGmN","cn_back-end_nestjs_开始.md":"_WpfLCID","cn_embedded-system_esp8266_mqtt-client.md":"E9D4SxF5","cn_front-end_frame_vue_index.md":"PjjfY2uG","cn_front-end_visual_leaflet_with-antdv-button.md":"ryuaCWex","packages_foo.md":"kss_QKHg","about-me.md":"3NYJ0eSJ","posts_index.md":"dpALkuP3","cn_back-end_nestjs_拦截器.md":"G5M7A3iW","cn_front-end_base_rank.md":"akyiuNKE","cn_front-end_base_书写规范.md":"yhX2TXYb","cn_back-end_nestjs_守卫.md":"WqFSRqzT","cn_embedded-system_esp8266_使用platformio通过网络控制led.md":"9MSNi_LW","cn_back-end_nestjs_自定义装饰器.md":"lO1-B4LO","posts_my-first-day.md":"zy70qzRE","cn_mx-components_common-components_按钮.md":"-3OHiFC-"}
